MANIFEST.in
README.md
setup.py
django_user_comments.egg-info/PKG-INFO
django_user_comments.egg-info/SOURCES.txt
django_user_comments.egg-info/dependency_links.txt
django_user_comments.egg-info/not-zip-safe
django_user_comments.egg-info/requires.txt
django_user_comments.egg-info/top_level.txt
user_comments/__init__.py
user_comments/models.py
user_comments/contrib/__init__.py
user_comments/contrib/is_core/__init__.py
user_comments/contrib/is_core/cores.py
user_comments/locale/cs/LC_MESSAGES/django.mo
user_comments/locale/cs/LC_MESSAGES/django.po
user_comments/migrations/0001_initial.py
user_comments/migrations/0002_migration.py
user_comments/migrations/__init__.py