Metadata-Version: 1.0
Name: django-user-comments
Version: 0.0.6
Summary: Library for adding comments of users related with object
Home-page: UNKNOWN
Author: Lubos Matl
Author-email: matllubos@gmail.com
License: UNKNOWN
Platform: UNKNOWN
